{
			"Authors" : ["brahmali"],
			"BookTitle" : "Dependent Liberation",
			"BookSubtitle" : "",
			"ShortAbstract" : "<p>This is a companion booklet to ‘Dependent Origination’ by the same author.</p>",
			"Abstract" : "<p>None</p>",
			"ItemType" : "document",
			"AddInfo"   : [["<p>Series</p>","<p>This is the second of two booklets in a series by Bhikkhu Brahmali.<br>Part 1 is: <a href='../dobl'><span data-custom-style='Hyperlink'>Dependent Origination</span></a></p>"],["<p>Overview</p>","<p>DEPENDENT LIBERATION:<br>(<span lang='pi'>lokuttara</span>-<span lang='pi'>paticcasamuppada</span>)<br><br>suffering (<span lang='pi'>dukkha</span>) ›<br>faith/confidence (<span lang='pi'>saddhā</span>) ›<br>gladness (<span lang='pi'>pāmojja</span>) ›<br>joy (<span lang='pi'>pīti</span>) ›<br>tranquillity (<span lang='pi'>passaddhi</span>) ›<br>happiness (<span lang='pi'>sukha</span>) ›<br>unification of mind (<span lang='pi'>samādhi</span>) ›<br>knowledge and vision according to reality (<span lang='pi'>yathā</span>-<span lang='pi'>bhūta</span>-<span lang='pi'>ñāṇa</span>-<span lang='pi'>dassana</span>) ›<br>repulsion (<span lang='pi'>nibbidā</span>) ›<br>dispassion (<span lang='pi'>virāga</span>) ›<br>liberation (<span lang='pi'>vimutti</span>) ›<br>knowledge that you are liberated (<span lang='pi'>khaye</span> <span lang='pi'>ñāṇaṁ</span>)</p>"]],
			"Copyright" : ["Originally published in 2013.","This edition published in 2021","Transcribed from a talk by Ajahn Brahmali, Dhammaloka, 23 March 2012.","Sourced from samita.be"],
			"CCLicense": "CC0 1.0",
			"FrontCover": "../_resources/book-data/dlbl/FrontLarge.jpg",
			"BackCover": "",
			"BackMatter": [""],
			"DownloadsAvailable": "pdf=yes,epub=yes,azw3=yes",
			"DownloadHTML": ""
		}