[
  {
    "zotref": "",
    "bookref": "Abeynayake"
  },
  {
    "zotref": "",
    "bookref": "Abhidharmasamuccaya"
  },
  {
    "zotref": "",
    "bookref": "Akanuma"
  },
  {
    "zotref": "",
    "bookref": "Anacker"
  },
  {
    "zotref": "",
    "bookref": "Anesaki"
  },
  {
    "zotref": "",
    "bookref": "Anālayo"
  },
  {
    "zotref": "",
    "bookref": "Anālayo (unpublished essay on M 32)"
  },
  {
    "zotref": "",
    "bookref": "Beal"
  },
  {
    "zotref": "",
    "bookref": "Beal (1985)"
  },
  {
    "zotref": "",
    "bookref": "Bodhi"
  },
  {
    "zotref": "",
    "bookref": "Boin-Webb"
  },
  {
    "zotref": "",
    "bookref": "Bronkhorst (1985)"
  },
  {
    "zotref": "",
    "bookref": "Bronkhorst (2000)"
  },
  {
    "zotref": "",
    "bookref": "Bucknell"
  },
  {
    "zotref": "",
    "bookref": "Buddhist Devotional Meditation"
  },
  {
    "zotref": "",
    "bookref": "Chang"
  },
  {
    "zotref": "",
    "bookref": "Choong"
  },
  {
    "zotref": "",
    "bookref": "Cleary"
  },
  {
    "zotref": "",
    "bookref": "Conze"
  },
  {
    "zotref": "",
    "bookref": "Cousins (1983)"
  },
  {
    "zotref": "",
    "bookref": "Crangle"
  },
  {
    "zotref": "",
    "bookref": "Dayal"
  },
  {
    "zotref": "",
    "bookref": "De Jong’s"
  },
  {
    "zotref": "",
    "bookref": "Dietz"
  },
  {
    "zotref": "",
    "bookref": "Dutt"
  },
  {
    "zotref": "",
    "bookref": "Enomoto"
  },
  {
    "zotref": "",
    "bookref": "Fa Tsang’s Brief Commentary"
  },
  {
    "zotref": "",
    "bookref": "Frauwallner (1995)"
  },
  {
    "zotref": "",
    "bookref": "Frauwallner 1956"
  },
  {
    "zotref": "",
    "bookref": "Gethin"
  },
  {
    "zotref": "",
    "bookref": "Gethin (2001)"
  },
  {
    "zotref": "",
    "bookref": "Gnoli"
  },
  {
    "zotref": "",
    "bookref": "Gombrich"
  },
  {
    "zotref": "",
    "bookref": "Harrison"
  },
  {
    "zotref": "",
    "bookref": "Heirmann"
  },
  {
    "zotref": "",
    "bookref": "Hopkins"
  },
  {
    "zotref": "",
    "bookref": "Kajiyama"
  },
  {
    "zotref": "",
    "bookref": "Keenan"
  },
  {
    "zotref": "",
    "bookref": "Kloppenborg"
  },
  {
    "zotref": "",
    "bookref": "Lamotte"
  },
  {
    "zotref": "",
    "bookref": "Lamotte (1976)"
  },
  {
    "zotref": "",
    "bookref": "Lamotte 1976"
  },
  {
    "zotref": "",
    "bookref": "Lamotte, 1983–4"
  },
  {
    "zotref": "",
    "bookref": "Letter to a Friend"
  },
  {
    "zotref": "",
    "bookref": "Li"
  },
  {
    "zotref": "",
    "bookref": "Lin"
  },
  {
    "zotref": "",
    "bookref": "Masefield"
  },
  {
    "zotref": "",
    "bookref": "Matsumura"
  },
  {
    "zotref": "",
    "bookref": "Meisig"
  },
  {
    "zotref": "",
    "bookref": "Minh Châu"
  },
  {
    "zotref": "",
    "bookref": "Nagao"
  },
  {
    "zotref": "",
    "bookref": "Nakamura"
  },
  {
    "zotref": "",
    "bookref": "Nhất Hạnh"
  },
  {
    "zotref": "",
    "bookref": "Norman 1979"
  },
  {
    "zotref": "",
    "bookref": "Nyanaponika"
  },
  {
    "zotref": "",
    "bookref": "Path to Deliverance"
  },
  {
    "zotref": "",
    "bookref": "Prasad"
  },
  {
    "zotref": "",
    "bookref": "Przylyski"
  },
  {
    "zotref": "",
    "bookref": "Przylyski 1923"
  },
  {
    "zotref": "",
    "bookref": "Rockhill"
  },
  {
    "zotref": "",
    "bookref": "Rāhula"
  },
  {
    "zotref": "",
    "bookref": "Samtani"
  },
  {
    "zotref": "",
    "bookref": "Saundarānanda Kāvya"
  },
  {
    "zotref": "",
    "bookref": "Schmithausen (1976)"
  },
  {
    "zotref": "",
    "bookref": "Schopen 1997"
  },
  {
    "zotref": "",
    "bookref": "Schopen 2004"
  },
  {
    "zotref": "",
    "bookref": "Smith"
  },
  {
    "zotref": "",
    "bookref": "Soma"
  },
  {
    "zotref": "",
    "bookref": "Sopa"
  },
  {
    "zotref": "",
    "bookref": "TEMPORARY ENTRY"
  },
  {
    "zotref": "",
    "bookref": "The Heart of Buddhist Meditation"
  },
  {
    "zotref": "",
    "bookref": "The Long Discourses of the Buddha"
  },
  {
    "zotref": "",
    "bookref": "Thiṭṭila"
  },
  {
    "zotref": "",
    "bookref": "Thiện Châu"
  },
  {
    "zotref": "",
    "bookref": "Tin"
  },
  {
    "zotref": "",
    "bookref": "Von Hinüber"
  },
  {
    "zotref": "",
    "bookref": "Waldschmidt (1950, 1951)"
  },
  {
    "zotref": "",
    "bookref": "Waldschmidt (1950–1951)"
  },
  {
    "zotref": "",
    "bookref": "Waldschmidt (1968)"
  },
  {
    "zotref": "",
    "bookref": "Walshe"
  },
  {
    "zotref": "",
    "bookref": "Warder"
  },
  {
    "zotref": "",
    "bookref": "Watanabe"
  },
  {
    "zotref": "",
    "bookref": "Wayman"
  },
  {
    "zotref": "",
    "bookref": "What the Buddha Taught"
  },
  {
    "zotref": "",
    "bookref": "Wijesekera"
  },
  {
    "zotref": "",
    "bookref": "Willis"
  },
  {
    "zotref": "",
    "bookref": "Wynne"
  },
  {
    "zotref": "",
    "bookref": "Yin Shun (1971)"
  },
  {
    "zotref": "",
    "bookref": "Yogic Direct Awareness"
  },
  {
    "zotref": "",
    "bookref": "Ñāṇamoli"
  },
  {
    "zotref": "",
    "bookref": "Ñāṇamoli (1964)"
  },
  {
    "zotref": "",
    "bookref": "Ñāṇamoli (1992)"
  },
  {
    "zotref": "",
    "bookref": "Ñāṇamoli’s"
  },
  {
    "zotref": "",
    "bookref": "Śikṣāsamuccaya"
  },
  {
    "zotref": "",
    "bookref": "Śikṣāsamuccaya, Kārikās"
  },
  {
    "zotref": "",
    "bookref": "Śrāvakabhūmi"
  }
]